faxina/__init__.py
faxina/components.py
faxina/core.py
faxina/input_controller.py
faxina/math3d.py
faxina/objects.py
faxina/render.py
faxina/scene.py
faxina/scenegraph.py
faxina/sceneloader.py
Faxina-1.0.dist-info/METADATA
Faxina-1.0.dist-info/WHEEL
Faxina-1.0.dist-info/top_level.txt
Faxina-1.0.dist-info/RECORD
