Metadata-Version: 2.1
Name: Faxina
Version: 1.0
Summary: Faxina - engine 3d for python 2.4. It Faxina Version not install on python x.3 and higher
Home-page: UNKNOWN
Author: Vladik
Author-email: vladhruzd25@gmail.com
License: UNKNOWN
Platform: UNKNOWN
Classifier: Programming Language :: Python :: 2.4
Classifier: License :: OSI Approved :: MIT License
Classifier: Operating System :: OS Independent
Requires-Python: >=2.4, <3
Requires-Dist: simplejson (==2.0.0)
